jupyterhub_chameleon/__init__.py
jupyterhub_chameleon/handler.py
jupyterhub_chameleon/spawner.py
jupyterhub_chameleon/utils.py
jupyterhub_chameleon/authenticator/__init__.py
jupyterhub_chameleon/authenticator/config.py
jupyterhub_chameleon/authenticator/keycloak.py
jupyterhub_chameleon/authenticator/openstack_oauth.py
jupyterhub_chameleon/service/__init__.py
jupyterhub_chameleon/service/cull_idle_servers.py
jupyterhub_chameleon-2.0.18.data/data/share/jupyterhub_chameleon/templates/auth_refresh.html
jupyterhub_chameleon-2.0.18.dist-info/LICENSE
jupyterhub_chameleon-2.0.18.dist-info/METADATA
jupyterhub_chameleon-2.0.18.dist-info/WHEEL
jupyterhub_chameleon-2.0.18.dist-info/entry_points.txt
jupyterhub_chameleon-2.0.18.dist-info/top_level.txt
jupyterhub_chameleon-2.0.18.dist-info/RECORD
