Metadata-Version: 2.1
Name: jupyterhub-chameleon
Version: 2.0.18
Summary: Chameleon extensions for JupyterHub
Home-page: https://github.com/chameleoncloud/jupyterhub-chameleon
Author: Jason Anderson
Author-email: jasonanderson@uchicago.edu
License: MIT
License-File: LICENSE
Requires-Dist: dockerspawner
Requires-Dist: jupyterhub
Requires-Dist: keystoneauth1
Requires-Dist: oauthenticator
Requires-Dist: python-keystoneclient
Requires-Dist: tornado
Requires-Dist: traitlets
